[
  {
    "title": "Ingénieur Data - IA H/FMeritis",
    "company": "Résultats prochesLes offres ci-dessous sont basées sur les mots-clés de votre recherche",
    "location": "Résultats prochesLes offres ci-dessous sont basées sur les mots-clés de votre recherche",
    "url": "https://www.hellowork.com/fr-fr/emplois/64903476.html",
    "source": "Hello Work",
    "publishedAt": "2026-07-21T17:13:33.611174+00:00"
  },
  {
    "title": "Ivvq Manager Lewis Engineering Agentic ai H/FThales",
    "company": "Ivvq Manager Lewis Engineering Agentic ai H/FThalesVélizy-Villacoublay - 78CDIVoir l’offreil y a 1 jour",
    "location": "Ivvq Manager Lewis Engineering Agentic ai H/FThalesVélizy-Villacoublay - 78CDIVoir l’offreil y a 1 jour",
    "url": "https://www.hellowork.com/fr-fr/emplois/79184640.html",
    "source": "Hello Work",
    "publishedAt": "2026-07-21T17:13:33.611174+00:00"
  },
  {
    "title": "Nounou 15 h/semaine à SEVRIER pour 2 enfants, 3 ans, 7 ans",
    "company": "Unknown",
    "location": "France",
    "url": "https://www.meteojob.com/jobs/55555279",
    "source": "Meteojob",
    "publishedAt": "2026-07-21T17:13:33.611174+00:00"
  },
  {
    "title": "Baby-sitter 5 h/semaine à SEYNOD pour 2 enfants, 3 ans, 7 ans",
    "company": "Unknown",
    "location": "France",
    "url": "https://www.meteojob.com/jobs/55555280",
    "source": "Meteojob",
    "publishedAt": "2026-07-21T17:13:33.611174+00:00"
  },
  {
    "title": "Garde d'enfant 6 h/semaine à VIUZ LA CHIESAZ pour 1 enfant, 3 ans",
    "company": "Unknown",
    "location": "France",
    "url": "https://www.meteojob.com/jobs/55555275",
    "source": "Meteojob",
    "publishedAt": "2026-07-21T17:13:33.611174+00:00"
  },
  {
    "title": "Garde d'enfant 7 h/semaine à CHATENAY MALABRY pour 2 enfants, 1 an, 3 ans",
    "company": "Unknown",
    "location": "France",
    "url": "https://www.meteojob.com/jobs/55555293",
    "source": "Meteojob",
    "publishedAt": "2026-07-21T17:13:33.611174+00:00"
  },
  {
    "title": "Garde d'enfant 6 h/semaine à VIROFLAY pour 2 enfants, 5 ans, 7 ans",
    "company": "Unknown",
    "location": "France",
    "url": "https://www.meteojob.com/jobs/55555288",
    "source": "Meteojob",
    "publishedAt": "2026-07-21T17:13:33.611174+00:00"
  },
  {
    "title": "Garde d'enfant 4 h/semaine à BOULOGNE BILLANCOURT pour 2 enfants, 2 ans, 9 ans",
    "company": "Unknown",
    "location": "France",
    "url": "https://www.meteojob.com/jobs/55555297",
    "source": "Meteojob",
    "publishedAt": "2026-07-21T17:13:33.611174+00:00"
  },
  {
    "title": "Baby-sitter 5 h/semaine à ST GERMAIN EN LAYE pour 2 enfants, 3 ans, 8 ans",
    "company": "Unknown",
    "location": "France",
    "url": "https://www.meteojob.com/jobs/55555271",
    "source": "Meteojob",
    "publishedAt": "2026-07-21T17:13:33.611174+00:00"
  },
  {
    "title": "Baby-sitter 6 h/semaine à COURBEVOIE pour 2 enfants, 4 ans, 6 ans",
    "company": "Unknown",
    "location": "France",
    "url": "https://www.meteojob.com/jobs/55555303",
    "source": "Meteojob",
    "publishedAt": "2026-07-21T17:13:33.611174+00:00"
  },
  {
    "title": "Garde d'enfant 17 h/semaine à ORVAULT pour 1 enfant, 10 ans",
    "company": "Unknown",
    "location": "France",
    "url": "https://www.meteojob.com/jobs/55555334",
    "source": "Meteojob",
    "publishedAt": "2026-07-21T17:13:33.611174+00:00"
  },
  {
    "title": "Nounou 4 h/semaine à LANGAN pour 2 enfants, 3 ans, 7 ans",
    "company": "Unknown",
    "location": "France",
    "url": "https://www.meteojob.com/jobs/55555325",
    "source": "Meteojob",
    "publishedAt": "2026-07-21T17:13:33.611174+00:00"
  },
  {
    "title": "Baby-sitter 6 h/semaine à VILLENEUVE LOUBET pour 1 enfant, 8 ans",
    "company": "Unknown",
    "location": "France",
    "url": "https://www.meteojob.com/jobs/55555321",
    "source": "Meteojob",
    "publishedAt": "2026-07-21T17:13:33.611174+00:00"
  },
  {
    "title": "Nounou 6 h/semaine à ALBIGNY SUR SAONE pour 2 enfants, 1 an, 3 ans",
    "company": "Unknown",
    "location": "France",
    "url": "https://www.meteojob.com/jobs/55555347",
    "source": "Meteojob",
    "publishedAt": "2026-07-21T17:13:33.611174+00:00"
  },
  {
    "title": "Nounou 4 h/semaine à ENGLOS pour 2 enfants, 7 ans, 11 ans",
    "company": "Unknown",
    "location": "France",
    "url": "https://www.meteojob.com/jobs/55555343",
    "source": "Meteojob",
    "publishedAt": "2026-07-21T17:13:33.611174+00:00"
  },
  {
    "title": "Baby-sitter 7 h/semaine à NOGENT SUR MARNE pour 1 enfant, 12 ans",
    "company": "Unknown",
    "location": "France",
    "url": "https://www.meteojob.com/jobs/55555361",
    "source": "Meteojob",
    "publishedAt": "2026-07-21T17:13:33.611174+00:00"
  },
  {
    "title": "Garde d'enfant 8 h/semaine à MEYREUIL pour 1 enfant, 4 ans",
    "company": "Unknown",
    "location": "France",
    "url": "https://www.meteojob.com/jobs/55555316",
    "source": "Meteojob",
    "publishedAt": "2026-07-21T17:13:33.611174+00:00"
  },
  {
    "title": "Responsable Partenariats Prescripteurs H/F",
    "company": "Unknown",
    "location": "France",
    "url": "https://www.meteojob.com/jobs/53658440",
    "source": "Meteojob",
    "publishedAt": "2026-07-21T17:13:33.611174+00:00"
  },
  {
    "title": "Chargé de recrutement H/F CDD Temps partiel",
    "company": "Unknown",
    "location": "France",
    "url": "https://www.meteojob.com/jobs/55270552",
    "source": "Meteojob",
    "publishedAt": "2026-07-21T17:13:33.611174+00:00"
  },
  {
    "title": "Chargé de recrutement H/F CDD Temps partiel",
    "company": "Unknown",
    "location": "France",
    "url": "https://www.meteojob.com/jobs/55277414",
    "source": "Meteojob",
    "publishedAt": "2026-07-21T17:13:33.611174+00:00"
  },
  {
    "title": "Chargé de Recrutement H/F CDD Bilingue",
    "company": "Unknown",
    "location": "France",
    "url": "https://www.meteojob.com/jobs/53914337",
    "source": "Meteojob",
    "publishedAt": "2026-07-21T17:13:33.611174+00:00"
  },
  {
    "title": "Garde d'enfant 14 h/semaine à NEUILLY SUR SEINE pour 2 enfants, 2 ans, 4 ans",
    "company": "Unknown",
    "location": "France",
    "url": "https://www.meteojob.com/jobs/55561849",
    "source": "Meteojob",
    "publishedAt": "2026-07-21T17:13:33.611174+00:00"
  },
  {
    "title": "Data Scientist IA – Développeur Machine Learning H/F",
    "company": "Crédit Agricole",
    "location": "Villejuif",
    "url": "https://www.welcometothejungle.com/fr/companies/groupe-credit-agricole/jobs/data-scientist-ia-developpeur-machine-learning-h-f_villejuif",
    "source": "Welcome to the Jungle",
    "publishedAt": "2026-07-08T09:02:01Z"
  },
  {
    "title": "Consultant Avant-Vente & Delivery IA - F/H",
    "company": "Atos",
    "location": "Bezons",
    "url": "https://www.welcometothejungle.com/fr/companies/atos/jobs/consultant-avant-vente-delivery-ia-f-h_bezons_ATOS_wJLGzD8",
    "source": "Welcome to the Jungle",
    "publishedAt": "2026-06-25T09:20:35Z",
    "salary": "€75k–90k"
  },
  {
    "title": "Ingénieur.e IA H/F",
    "company": "VIGINUM",
    "location": "Paris",
    "url": "https://www.welcometothejungle.com/fr/companies/viginum/jobs/ingenieur-e-ia-h-f_paris",
    "source": "Welcome to the Jungle",
    "publishedAt": "2026-06-09T14:18:48Z"
  },
  {
    "title": "Docteur en IA Embarquée / FPGA / Computer Vision - (F/H)",
    "company": "Groupe SII",
    "location": "Toulouse",
    "url": "https://www.welcometothejungle.com/fr/companies/sii/jobs/docteur-en-ia-embarquee-fpga-computer-vision-f-h_toulouse_GS_75ZLDxe",
    "source": "Welcome to the Jungle",
    "publishedAt": "2026-05-26T12:35:33Z",
    "salary": "€38k–42k"
  }
]