[
  {
    "title": "Ingénieur Data - IA H/FMeritis",
    "company": "Résultats prochesLes offres ci-dessous sont basées sur les mots-clés de votre recherche",
    "location": "Résultats prochesLes offres ci-dessous sont basées sur les mots-clés de votre recherche",
    "url": "https://www.hellowork.com/fr-fr/emplois/64903476.html",
    "source": "Hello Work",
    "publishedAt": "2026-07-14T05:25:36.925610+00:00"
  },
  {
    "title": "Ivvq Manager Lewis Engineering Agentic ai H/FThales",
    "company": "Ivvq Manager Lewis Engineering Agentic ai H/FThalesVélizy-Villacoublay - 78CDIVoir l’offreil y a 25 jours",
    "location": "Ivvq Manager Lewis Engineering Agentic ai H/FThalesVélizy-Villacoublay - 78CDIVoir l’offreil y a 25 jours",
    "url": "https://www.hellowork.com/fr-fr/emplois/79184640.html",
    "source": "Hello Work",
    "publishedAt": "2026-07-14T05:25:36.925610+00:00"
  },
  {
    "title": "Nounou 7 h/semaine à SARTROUVILLE pour 1 enfant, 2 ans",
    "company": "Unknown",
    "location": "France",
    "url": "https://www.meteojob.com/jobs/55416970",
    "source": "Meteojob",
    "publishedAt": "2026-07-14T05:25:36.925610+00:00"
  },
  {
    "title": "Baby-sitter 6 h/semaine à NEUILLY SUR SEINE pour 2 enfants, 6 ans, 8 ans",
    "company": "Unknown",
    "location": "France",
    "url": "https://www.meteojob.com/jobs/55417007",
    "source": "Meteojob",
    "publishedAt": "2026-07-14T05:25:36.925610+00:00"
  },
  {
    "title": "Nounou 4 h/semaine à SARTROUVILLE pour 2 enfants, 3 ans, 6 ans",
    "company": "Unknown",
    "location": "France",
    "url": "https://www.meteojob.com/jobs/55416969",
    "source": "Meteojob",
    "publishedAt": "2026-07-14T05:25:36.925610+00:00"
  },
  {
    "title": "Baby-sitter 8 h/semaine à LE MESNIL LE ROI pour 3 enfants, 8 ans, 11 ans",
    "company": "Unknown",
    "location": "France",
    "url": "https://www.meteojob.com/jobs/55416965",
    "source": "Meteojob",
    "publishedAt": "2026-07-14T05:25:36.925610+00:00"
  },
  {
    "title": "Nounou 8 h/semaine à MARSEILLE(13) pour 2 enfants, 2 ans, 3 ans",
    "company": "Unknown",
    "location": "France",
    "url": "https://www.meteojob.com/jobs/55417034",
    "source": "Meteojob",
    "publishedAt": "2026-07-14T05:25:36.925610+00:00"
  },
  {
    "title": "Garde d'enfant 4 h/semaine à ECQUEVILLY pour 2 enfants, 5 ans, 8 ans",
    "company": "Unknown",
    "location": "France",
    "url": "https://www.meteojob.com/jobs/55416961",
    "source": "Meteojob",
    "publishedAt": "2026-07-14T05:25:36.925610+00:00"
  },
  {
    "title": "Baby-sitter 12 h/semaine à ST CLOUD pour 1 enfant, 1 an",
    "company": "Unknown",
    "location": "France",
    "url": "https://www.meteojob.com/jobs/55416996",
    "source": "Meteojob",
    "publishedAt": "2026-07-14T05:25:36.925610+00:00"
  },
  {
    "title": "Garde d'enfant 6 h/semaine à ASNIERES SUR SEINE pour 1 enfant, 4 ans",
    "company": "Unknown",
    "location": "France",
    "url": "https://www.meteojob.com/jobs/55417012",
    "source": "Meteojob",
    "publishedAt": "2026-07-14T05:25:36.925610+00:00"
  },
  {
    "title": "Baby-sitter 6 h/semaine à CHATOU pour 1 enfant, 5 ans",
    "company": "Unknown",
    "location": "France",
    "url": "https://www.meteojob.com/jobs/55416974",
    "source": "Meteojob",
    "publishedAt": "2026-07-14T05:25:36.925610+00:00"
  },
  {
    "title": "Garde d'enfant 4 h/semaine à LANGOIRAN pour 2 enfants, 6 ans, 11 ans",
    "company": "Unknown",
    "location": "France",
    "url": "https://www.meteojob.com/jobs/55417030",
    "source": "Meteojob",
    "publishedAt": "2026-07-14T05:25:36.925610+00:00"
  },
  {
    "title": "Garde d'enfant 4 h/semaine à ST LAURENT DU VAR pour 2 enfants, 5 ans, 8 ans",
    "company": "Unknown",
    "location": "France",
    "url": "https://www.meteojob.com/jobs/55417025",
    "source": "Meteojob",
    "publishedAt": "2026-07-14T05:25:36.925610+00:00"
  },
  {
    "title": "Nounou 2 h/semaine à MEYZIEU pour 1 enfant, 10 ans",
    "company": "Unknown",
    "location": "France",
    "url": "https://www.meteojob.com/jobs/55417056",
    "source": "Meteojob",
    "publishedAt": "2026-07-14T05:25:36.925610+00:00"
  },
  {
    "title": "Garde d'enfant 12 h/semaine à LOUVECIENNES pour 1 enfant, 8 ans",
    "company": "Unknown",
    "location": "France",
    "url": "https://www.meteojob.com/jobs/55416987",
    "source": "Meteojob",
    "publishedAt": "2026-07-14T05:25:36.925610+00:00"
  },
  {
    "title": "Nounou 6 h/semaine à PERTUIS pour 1 enfant, 5 ans",
    "company": "Unknown",
    "location": "France",
    "url": "https://www.meteojob.com/jobs/55417021",
    "source": "Meteojob",
    "publishedAt": "2026-07-14T05:25:36.925610+00:00"
  },
  {
    "title": "Garde d'enfant 4 h/semaine à EPAGNY pour 2 enfants, 6 ans, 10 ans",
    "company": "Unknown",
    "location": "France",
    "url": "https://www.meteojob.com/jobs/55416983",
    "source": "Meteojob",
    "publishedAt": "2026-07-14T05:25:36.925610+00:00"
  },
  {
    "title": "Garde d'enfant 6 h/semaine à PARIS(11) pour 2 enfants, 2 ans, 4 ans",
    "company": "Unknown",
    "location": "France",
    "url": "https://www.meteojob.com/jobs/55417016",
    "source": "Meteojob",
    "publishedAt": "2026-07-14T05:25:36.925610+00:00"
  },
  {
    "title": "Garde d'enfant 4 h/semaine à MARCQ EN BAROEUL pour 2 enfants, 9 ans, 11 ans",
    "company": "Unknown",
    "location": "France",
    "url": "https://www.meteojob.com/jobs/55417052",
    "source": "Meteojob",
    "publishedAt": "2026-07-14T05:25:36.925610+00:00"
  },
  {
    "title": "Nounou 8 h/semaine à METZ TESSY pour 3 enfants, 3 ans, 6 ans, 8 ans",
    "company": "Unknown",
    "location": "France",
    "url": "https://www.meteojob.com/jobs/55416978",
    "source": "Meteojob",
    "publishedAt": "2026-07-14T05:25:36.925610+00:00"
  },
  {
    "title": "Garde d'enfant 8 h/semaine à SAUBENS pour 1 enfant, 4 ans",
    "company": "Unknown",
    "location": "France",
    "url": "https://www.meteojob.com/jobs/55417047",
    "source": "Meteojob",
    "publishedAt": "2026-07-14T05:25:36.925610+00:00"
  },
  {
    "title": "Garde d'enfant 6 h/semaine à VAUX SUR SEINE pour 1 enfant, 1 an",
    "company": "Unknown",
    "location": "France",
    "url": "https://www.meteojob.com/jobs/55417061",
    "source": "Meteojob",
    "publishedAt": "2026-07-14T05:25:36.925610+00:00"
  },
  {
    "title": "Data Scientist IA – Développeur Machine Learning H/F",
    "company": "Groupe Crédit Agricole",
    "location": "Villejuif",
    "url": "https://www.welcometothejungle.com/fr/companies/groupe-credit-agricole/jobs/data-scientist-ia-developpeur-machine-learning-h-f_villejuif",
    "source": "Welcome to the Jungle",
    "publishedAt": "2026-07-08T09:02:01Z"
  },
  {
    "title": "Consultant Avant-Vente & Delivery IA - F/H",
    "company": "Atos",
    "location": "Bezons",
    "url": "https://www.welcometothejungle.com/fr/companies/atos/jobs/consultant-avant-vente-delivery-ia-f-h_bezons_ATOS_wJLGzD8",
    "source": "Welcome to the Jungle",
    "publishedAt": "2026-06-25T09:20:35Z",
    "salary": "€75k–90k"
  },
  {
    "title": "Ingénieur.e IA H/F",
    "company": "VIGINUM",
    "location": "Paris",
    "url": "https://www.welcometothejungle.com/fr/companies/viginum/jobs/ingenieur-e-ia-h-f_paris",
    "source": "Welcome to the Jungle",
    "publishedAt": "2026-06-09T14:18:48Z"
  },
  {
    "title": "Docteur en IA Embarquée / FPGA / Computer Vision - (F/H)",
    "company": "Groupe SII",
    "location": "Toulouse",
    "url": "https://www.welcometothejungle.com/fr/companies/sii/jobs/docteur-en-ia-embarquee-fpga-computer-vision-f-h_toulouse_GS_75ZLDxe",
    "source": "Welcome to the Jungle",
    "publishedAt": "2026-05-26T12:35:33Z",
    "salary": "€38k–42k"
  }
]