[
  {
    "title": "Ingénieur Data - IA H/FMeritis",
    "company": "Résultats prochesLes offres ci-dessous sont basées sur les mots-clés de votre recherche",
    "location": "Résultats prochesLes offres ci-dessous sont basées sur les mots-clés de votre recherche",
    "url": "https://www.hellowork.com/fr-fr/emplois/64903476.html",
    "source": "Hello Work",
    "publishedAt": "2026-06-14T09:27:51.946729+00:00"
  },
  {
    "title": "Ivvq Manager Lewis Engineering Agentic ai H/FThales",
    "company": "Ivvq Manager Lewis Engineering Agentic ai H/FThalesVélizy-Villacoublay - 78CDIVoir l’offreil y a 25 jours",
    "location": "Ivvq Manager Lewis Engineering Agentic ai H/FThalesVélizy-Villacoublay - 78CDIVoir l’offreil y a 25 jours",
    "url": "https://www.hellowork.com/fr-fr/emplois/79184640.html",
    "source": "Hello Work",
    "publishedAt": "2026-06-14T09:27:51.946729+00:00"
  },
  {
    "title": "Nounou 14 h/semaine à ST JEAN DE BOISEAU pour 2 enfants, 1 an, 4 ans",
    "company": "Unknown",
    "location": "France",
    "url": "https://www.meteojob.com/jobs/54657720",
    "source": "Meteojob",
    "publishedAt": "2026-06-14T09:27:51.946729+00:00"
  },
  {
    "title": "Chaudronnier Soudeur (h/f)",
    "company": "Unknown",
    "location": "France",
    "url": "https://www.meteojob.com/jobs/54658215",
    "source": "Meteojob",
    "publishedAt": "2026-06-14T09:27:51.946729+00:00"
  },
  {
    "title": "Conducteur de ligne (h/f)",
    "company": "Unknown",
    "location": "France",
    "url": "https://www.meteojob.com/jobs/54658233",
    "source": "Meteojob",
    "publishedAt": "2026-06-14T09:27:51.946729+00:00"
  },
  {
    "title": "Chauffeur PL Nuit (h/f)",
    "company": "Unknown",
    "location": "France",
    "url": "https://www.meteojob.com/jobs/54658228",
    "source": "Meteojob",
    "publishedAt": "2026-06-14T09:27:51.946729+00:00"
  },
  {
    "title": "Conducteur d'Engins de Chantier R482 – F (h/f)",
    "company": "Unknown",
    "location": "France",
    "url": "https://www.meteojob.com/jobs/54658206",
    "source": "Meteojob",
    "publishedAt": "2026-06-14T09:27:51.946729+00:00"
  },
  {
    "title": "Chef d'Équipe chaudronnier monteur (h/f)",
    "company": "Unknown",
    "location": "France",
    "url": "https://www.meteojob.com/jobs/54658202",
    "source": "Meteojob",
    "publishedAt": "2026-06-14T09:27:51.946729+00:00"
  },
  {
    "title": "Coordinateur de Travaux (h/f)",
    "company": "Unknown",
    "location": "France",
    "url": "https://www.meteojob.com/jobs/54658211",
    "source": "Meteojob",
    "publishedAt": "2026-06-14T09:27:51.946729+00:00"
  },
  {
    "title": "Technicien de Maintenance (h/f)",
    "company": "Unknown",
    "location": "France",
    "url": "https://www.meteojob.com/jobs/54672165",
    "source": "Meteojob",
    "publishedAt": "2026-06-14T09:27:51.946729+00:00"
  },
  {
    "title": "Chargé d'accueil H/F CDD",
    "company": "Unknown",
    "location": "France",
    "url": "https://www.meteojob.com/jobs/54686650",
    "source": "Meteojob",
    "publishedAt": "2026-06-14T09:27:51.946729+00:00"
  },
  {
    "title": "Conseiller clientèle H/F",
    "company": "Unknown",
    "location": "France",
    "url": "https://www.meteojob.com/jobs/54686649",
    "source": "Meteojob",
    "publishedAt": "2026-06-14T09:27:51.946729+00:00"
  },
  {
    "title": "Chargé d'accueil H/F CDD",
    "company": "Unknown",
    "location": "France",
    "url": "https://www.meteojob.com/jobs/54686645",
    "source": "Meteojob",
    "publishedAt": "2026-06-14T09:27:51.946729+00:00"
  },
  {
    "title": "Vendeur Magasin (h/f)",
    "company": "Unknown",
    "location": "France",
    "url": "https://www.meteojob.com/jobs/54688966",
    "source": "Meteojob",
    "publishedAt": "2026-06-14T09:27:51.946729+00:00"
  },
  {
    "title": "Soudeur (h/f)",
    "company": "Unknown",
    "location": "France",
    "url": "https://www.meteojob.com/jobs/54691322",
    "source": "Meteojob",
    "publishedAt": "2026-06-14T09:27:51.946729+00:00"
  },
  {
    "title": "Peintre Industriel (h/f)",
    "company": "Unknown",
    "location": "France",
    "url": "https://www.meteojob.com/jobs/54691317",
    "source": "Meteojob",
    "publishedAt": "2026-06-14T09:27:51.946729+00:00"
  },
  {
    "title": "Technicien Électricien de Maintenance (h/f)",
    "company": "Unknown",
    "location": "France",
    "url": "https://www.meteojob.com/jobs/54691308",
    "source": "Meteojob",
    "publishedAt": "2026-06-14T09:27:51.946729+00:00"
  },
  {
    "title": "Cariste (h/f)",
    "company": "Unknown",
    "location": "France",
    "url": "https://www.meteojob.com/jobs/54691313",
    "source": "Meteojob",
    "publishedAt": "2026-06-14T09:27:51.946729+00:00"
  },
  {
    "title": "Conducteur Poids Lourds (h/f)",
    "company": "Unknown",
    "location": "France",
    "url": "https://www.meteojob.com/jobs/54691078",
    "source": "Meteojob",
    "publishedAt": "2026-06-14T09:27:51.946729+00:00"
  },
  {
    "title": "Centralier (h/f)",
    "company": "Unknown",
    "location": "France",
    "url": "https://www.meteojob.com/jobs/54691074",
    "source": "Meteojob",
    "publishedAt": "2026-06-14T09:27:51.946729+00:00"
  },
  {
    "title": "Gestionnaire Administration du Personnel (h/f)",
    "company": "Unknown",
    "location": "France",
    "url": "https://www.meteojob.com/jobs/54691092",
    "source": "Meteojob",
    "publishedAt": "2026-06-14T09:27:51.946729+00:00"
  },
  {
    "title": "Cariste - Pontier (h/f)",
    "company": "Unknown",
    "location": "France",
    "url": "https://www.meteojob.com/jobs/54691087",
    "source": "Meteojob",
    "publishedAt": "2026-06-14T09:27:51.946729+00:00"
  },
  {
    "title": "Ingénieur.e IA H/F",
    "company": "VIGINUM",
    "location": "Paris",
    "url": "https://www.welcometothejungle.com/fr/companies/viginum/jobs/ingenieur-e-ia-h-f_paris",
    "source": "Welcome to the Jungle",
    "publishedAt": "2026-06-09T14:18:48Z"
  },
  {
    "title": "Développeur IA Générative / Generative AI Engineer H/F",
    "company": "The Adecco Group",
    "location": "Paris",
    "url": "https://www.welcometothejungle.com/fr/companies/the-adecco-group/jobs/developpeur-ia-generative-generative-ai-engineer-h-f_paris_TAG_xz2owqm",
    "source": "Welcome to the Jungle",
    "publishedAt": "2026-06-01T15:24:20Z"
  },
  {
    "title": "Docteur en IA Embarquée / FPGA / Computer Vision - F/H",
    "company": "Groupe SII",
    "location": "Toulouse",
    "url": "https://www.welcometothejungle.com/fr/companies/sii/jobs/docteur-en-ia-embarquee-fpga-computer-vision-f-h_toulouse_GS_75ZLDxe",
    "source": "Welcome to the Jungle",
    "publishedAt": "2026-05-26T12:35:33Z",
    "salary": "€38k–42k"
  },
  {
    "title": "Data Scientist IA – Développeur Machine Learning H/F",
    "company": "Groupe Crédit Agricole",
    "location": "Villejuif",
    "url": "https://www.welcometothejungle.com/fr/companies/groupe-credit-agricole/jobs/data-scientist-ia-developpeur-machine-learning-h-f_villejuif",
    "source": "Welcome to the Jungle",
    "publishedAt": "2026-05-06T09:02:17Z"
  }
]